LICENSE
MANIFEST.in
README.md
setup.py
bin/pypssl
pypssl/__init__.py
pypssl/api.py
pypssl.egg-info/PKG-INFO
pypssl.egg-info/SOURCES.txt
pypssl.egg-info/dependency_links.txt
pypssl.egg-info/requires.txt
pypssl.egg-info/top_level.txt