Metadata-Version: 1.1
Name: pypssl
Version: 2.1
Summary: Python API for PSSL.
Home-page: https://github.com/adulau/crl-monitor/tree/master/client
Author: Raphaël Vinot
Author-email: raphael.vinot@circl.lu
License: UNKNOWN
Platform: UNKNOWN
Classifier: License :: OSI Approved :: GNU General Public License v3 (GPLv3)
Classifier: Development Status :: 5 - Production/Stable
Classifier: Environment :: Console
Classifier: Intended Audience :: Science/Research
Classifier: Intended Audience :: Telecommunications Industry
Classifier: Programming Language :: Python :: 2.7
Classifier: Programming Language :: Python :: 3
Classifier: Topic :: Security
Classifier: Topic :: Internet
